{
  "parent": "minecraft:recipes/root",
  "rewards": {
    "recipes": [
      "mythicbotany:mana_collector"
    ]
  },
  "criteria": {
    "criterion0": {
      "trigger": "minecraft:inventory_changed",
      "conditions": {
        "items": [
          {
            "items": [
              "botania:glimmering_dreamwood"
            ]
          }
        ]
      }
    },
    "criterion1": {
      "trigger": "minecraft:inventory_changed",
      "conditions": {
        "items": [
          {
            "items": [
              "botania:gaia_ingot"
            ]
          }
        ]
      }
    },
    "criterion2": {
      "trigger": "minecraft:inventory_changed",
      "conditions": {
        "items": [
          {
            "items": [
              "botania:pixie_dust"
            ]
          }
        ]
      }
    },
    "criterion3": {
      "trigger": "minecraft:inventory_changed",
      "conditions": {
        "items": [
          {
            "items": [
              "mythicbotany:vanaheim_rune"
            ]
          }
        ]
      }
    },
    "has_the_recipe": {
      "trigger": "minecraft:recipe_unlocked",
      "conditions": {
        "recipe": "mythicbotany:mana_collector"
      }
    }
  },
  "requirements": [
    [
      "criterion0",
      "criterion1",
      "criterion2",
      "criterion3",
      "has_the_recipe"
    ]
  ]
}